[
  {
    "page_number": 22,
    "bbox": [
      47.49,
      123.6,
      156.83,
      148.08
    ],
    "text": "CD4 r tc, O \u00ae CIC. Cls 0 CDC en\u017c \"'",
    "fonts": [
      "*Arial-Bold-9625",
      "*Arial-Bold-9626"
    ],
    "sizes": [
      6.5,
      9.000006675720215
    ]
  },
  {
    "page_number": 22,
    "bbox": [
      48.61,
      122.38,
      158.9,
      165.7
    ],
    "text": "\u017d c <> J> a, Q \u00b0' \u00ae @> &(I) 1\u00a3 !to a t1. t u o. gCD",
    "fonts": [
      "*Arial-Bold-9625",
      "*Arial-Bold-9626",
      "*Times New Roman-9602",
      "*Times New Roman-9607",
      "*Times New Roman-Italic-9624"
    ],
    "sizes": [
      6.49996280670166,
      6.5,
      8.99994945526123,
      9.0,
      14.5,
      15.0,
      16.0
    ]
  },
  {
    "page_number": 22,
    "bbox": [
      48.88,
      145.94,
      158.2,
      178.08
    ],
    "text": "'gvt)!J. 9lg w9g J . oCI\u017e ic .l\"4 Cl*g_ dJ",
    "fonts": [
      "*Arial-Bold-9625",
      "*Arial-Bold-9626",
      "*Arial-Bold-9630",
      "*Times New Roman-9598",
      "*Times New Roman-Italic-9616"
    ],
    "sizes": [
      4.0,
      6.0,
      6.000072002410889,
      6.5,
      9.0
    ]
  },
  {
    "page_number": 22,
    "bbox": [
      39.41,
      179.91,
      161.36,
      224.93
    ],
    "text": "GIG)4 G {bQ4 C,c,J l w \u0002 @) \u017f], &. \u0180 \u0181 \u0182ftc,i\u0183:.g g\u00b7 :",
    "fonts": [
      "*Arial-Bold-9625",
      "*Arial-Bold-9626",
      "*Times New Roman-9614",
      "*Times New Roman-9623",
      "*Times New Roman-Italic-9622"
    ],
    "sizes": [
      6.5,
      9.0,
      9.000215530395508,
      19.000455856323242,
      20.0,
      23.0
    ]
  },
  {
    "page_number": 22,
    "bbox": [
      37.61,
      206.34,
      158.97,
      299.87
    ],
    "text": "@) .P g !:b c,i g c, \u2022 G> ;51 GG1.N..-.. 9o.ic,ia S> ,gg .::: ./'\\ ,GI &O G\\ C)4 a_tt C, c,iu (1;i@)G &_<\u00a7 COu.. G\\ (DO 9_4 \u0184i\u0185\u00ae!taao\u0186cg g-E g_& \u0004 9 0 a \u0187uc9 c, .I'\\ GI U..o_g g",
    "fonts": [
      "*Arial-Bold-9625",
      "*Arial-Bold-9626",
      "*Arial-Bold-9627",
      "*Times New Roman-9598",
      "*Times New Roman-9607",
      "*Times New Roman-9614",
      "*Times New Roman-9618",
      "*Times New Roman-Italic-9621"
    ],
    "sizes": [
      5.999971866607666,
      6.0,
      6.000181198120117,
      6.5,
      8.999958038330078,
      9.0,
      9.000271797180176,
      13.00039291381836,
      14.0,
      16.0,
      19.0
    ]
  },
  {
    "page_number": 22,
    "bbox": [
      37.37,
      282.27,
      157.72,
      311.36
    ],
    "text": "c,i,.9- c,i ft 'ilJ a \u00ae a 4 g",
    "fonts": [
      "*Arial-Bold-9626",
      "*Times New Roman-9598",
      "*Times New Roman-Italic-9620"
    ],
    "sizes": [
      6.0,
      9.0,
      13.0
    ]
  },
  {
    "page_number": 22,
    "bbox": [
      36.14,
      293.79,
      158.74,
      351.8
    ],
    "text": "G (ll a> G> \u0188 \u001b\u0189 cg G g,caCl','=-'Gla G\\ e&Qc, oc G\\ga'9 Rg\u00aeci; ;:0 <9tc, cfgJ-\u018a\u018bcg\u0016nc",
    "fonts": [
      "*Arial-Bold-9625",
      "*Arial-Bold-9626",
      "*Arial-Bold-9627",
      "*Times New Roman-9598",
      "*Times New Roman-9601"
    ],
    "sizes": [
      6.0,
      6.5,
      9.0,
      17.0
    ]
  },
  {
    "page_number": 22,
    "bbox": [
      49.03,
      336.26,
      158.56,
      385.75
    ],
    "text": "a,.9-B 9. \u00aew Sl@ G g Gl GI G\\ G\\ g Q, G \u00b0'\"' G 8 g G G g_ ft t0 g_ au.. @,9 ..r,",
    "fonts": [
      "*Arial-Bold-9625",
      "*Arial-Bold-9626",
      "*Arial-Bold-9627",
      "*Arial-Italic-9628",
      "*Times New Roman-9601",
      "*Times New Roman-9618",
      "*Times New Roman-Italic-9606"
    ],
    "sizes": [
      6.0,
      6.5,
      8.0,
      9.0,
      13.0,
      17.0
    ]
  },
  {
    "page_number": 22,
    "bbox": [
      171.2,
      177.92,
      189.93,
      205.51
    ],
    "text": "\u018c g",
    "fonts": [
      "*Arial-Bold-9626"
    ],
    "sizes": [
      9.0
    ]
  },
  {
    "page_number": 22,
    "bbox": [
      168.45,
      196.2,
      205.17,
      226.34
    ],
    "text": "jcc, \u018d !:b O '-'",
    "fonts": [
      "*Arial-Bold-9625",
      "*Arial-Bold-9626"
    ],
    "sizes": [
      6.500078201293945,
      9.0,
      9.000107765197754
    ]
  },
  {
    "page_number": 22,
    "bbox": [
      167.28,
      210.18,
      207.25,
      292.85
    ],
    "text": "c, c, : g CQ !:b \u00b0' @) Cl g_ G\\ \u00b0' ca.9 \u0003\u00ae :20 a G",
    "fonts": [
      "*Arial-Bold-9625",
      "*Arial-Bold-9626",
      "*Times New Roman-9598",
      "*Times New Roman-9601",
      "*Times New Roman-Italic-9611",
      "*Times New Roman-Italic-9619"
    ],
    "sizes": [
      6.000072002410889,
      6.5,
      9.0,
      9.000107765197754,
      10.0,
      17.0,
      17.00020408630371,
      23.0
    ]
  },
  {
    "page_number": 22,
    "bbox": [
      166.64,
      273.83,
      208.0,
      331.2
    ],
    "text": "G x u c, c, C& \u00b0' !:t\u0002 B o G @ \u00ae",
    "fonts": [
      "*Arial-Bold-9625",
      "*Arial-Bold-9626",
      "*Courier New-9633",
      "*Times New Roman-9601",
      "*Times New Roman-9609"
    ],
    "sizes": [
      5.000060081481934,
      6.5,
      9.0,
      9.000107765197754,
      17.0,
      18.0
    ]
  },
  {
    "page_number": 22,
    "bbox": [
      170.27,
      315.86,
      202.77,
      335.58
    ],
    "text": "\u00b7 8. 0",
    "fonts": [
      "*Arial-Bold-9625"
    ],
    "sizes": [
      6.5
    ]
  },
  {
    "page_number": 22,
    "bbox": [
      179.73,
      330.71,
      204.61,
      359.47
    ],
    "text": "-0 ; + G\\ @ G",
    "fonts": [
      "*Arial-Bold-9625",
      "*Arial-Bold-9626",
      "*Times New Roman-9598"
    ],
    "sizes": [
      6.0,
      6.5,
      9.0
    ]
  },
  {
    "page_number": 22,
    "bbox": [
      178.25,
      345.04,
      201.58,
      379.41
    ],
    "text": "g g_G oc,",
    "fonts": [
      "*Arial-Bold-9626"
    ],
    "sizes": [
      9.0
    ]
  },
  {
    "page_number": 22,
    "bbox": [
      320.6,
      126.95,
      379.87,
      144.07
    ],
    "text": "\u00a3\"\"0\u00ae",
    "fonts": [
      "*Times New Roman-9595"
    ],
    "sizes": [
      10.999948501586914
    ]
  },
  {
    "page_number": 22,
    "bbox": [
      322.89,
      135.37,
      379.85,
      169.86
    ],
    "text": "c:,rniR'\u000eB m yCl gt",
    "fonts": [
      "*Arial-Bold-9625",
      "*Arial-Bold-9630",
      "*Times New Roman-9595"
    ],
    "sizes": [
      4.0,
      6.5,
      11.000200271606445
    ]
  },
  {
    "page_number": 22,
    "bbox": [
      332.14,
      143.57,
      378.92,
      186.33
    ],
    "text": ". Cl Cl ..9-g_g <J. \u00b0' a o19",
    "fonts": [
      "*Arial-Bold-9625",
      "*Arial-Bold-9626",
      "*Arial-Bold-9630",
      "*Times New Roman-9598",
      "*Times New Roman-9618"
    ],
    "sizes": [
      4.0,
      6.0,
      6.5,
      9.0,
      13.0
    ]
  },
  {
    "page_number": 22,
    "bbox": [
      208.57,
      178.21,
      365.48,
      215.8
    ],
    "text": "C, 6 0 z Gl GI .NJ O G\\ .l'{),r, g Cl Reg a 9'\"fu9 \u00aegage> o.i .., ,.,o. G\\ ctC>g0",
    "fonts": [
      "*Arial-Bold-9625",
      "*Arial-Bold-9626",
      "*Arial-Bold-9627",
      "*Times New Roman-9598",
      "*Times New Roman-Italic-9615",
      "*Verdana-Bold-9634"
    ],
    "sizes": [
      6.0,
      6.5,
      7.0,
      9.0
    ]
  },
  {
    "page_number": 22,
    "bbox": [
      210.35,
      189.13,
      379.07,
      276.92
    ],
    "text": "8}C \u018eoo\"' Gl ;:, u g t-!) ,.s>- 'w-0 0.@ aocrn c;_g\u018f!]) g uC>G1 9.Cl'ic; \u00a74cr0.g,g\u0190gRJg a[..%\u0191C>c,i\u00ae::::, G\\ g g G\\ \u00b0' . CJ; a c; \u00ae .....,Gl { ,9- c, 0 \\'Cl Cl; c,i\u00b7 CS\u0192\"'20g ig\u00a7lJa G g g G'fu@gi \u0193@go. 4 -9 @ o.9e&c\u0194c,i",
    "fonts": [
      "*Arial-Bold-9625",
      "*Arial-Bold-9626",
      "*Arial-Bold-9627",
      "*Times New Roman-9598",
      "*Times New Roman-9601",
      "*Times New Roman-9610",
      "*Times New Roman-Italic-9617"
    ],
    "sizes": [
      4.0,
      6.0,
      6.000050067901611,
      6.5,
      8.0,
      9.0,
      9.000075340270996,
      17.0
    ]
  },
  {
    "page_number": 22,
    "bbox": [
      210.58,
      258.22,
      379.04,
      317.89
    ],
    "text": ".I'{). G S\u0016 a;Cd.QiN @ N N \u00b0'\" -0 Q_ \b .(1/ N (Cl ',>.. v cs '\"'\u0016 '-\"\u2022\u00ab\"U gQQ 9'\"\"u OJ rn a G\\ w i - g .r,\u00b7 '\"fu i p. a \u0002 \u00aeC) Q .l'{)U g CJ@) c,\u00a3!>0-(, \u001ba,Ogc, C!o @JC'JQo_ GGu",
    "fonts": [
      "*Arial-Bold-9625",
      "*Arial-Bold-9626",
      "*Arial-Bold-9627",
      "*Arial-Bold-9630",
      "*Arial-Italic-9628",
      "*Times New Roman-9598",
      "*Times New Roman-9610",
      "*Times New Roman-9613",
      "*Times New Roman-9614",
      "*Times New Roman-Italic-9606",
      "*Times New Roman-Italic-9615",
      "*Times New Roman-Italic-9616",
      "*Verdana-Bold-9634"
    ],
    "sizes": [
      4.0,
      6.0,
      6.5,
      7.0,
      8.0,
      9.0,
      15.0,
      19.0
    ]
  },
  {
    "page_number": 22,
    "bbox": [
      208.44,
      298.01,
      378.84,
      380.37
    ],
    "text": "- G\\@C> CCl n..r.G.gCl <D \u0195- g G O \u0196 SJ @) \u00a7 g \u0197- c,i ft_l3 c\u00bb ct !3) 9.. .r. g g u.. G. ,.9'- G\\ \u00a3!> \u00a3!> CJ U@ 9c G\\\u0198g<!t CJ; G [ 0 CS c,i,.9'-,g .NJ @J \u00b0' c, gC& CJ 9. O G G. <11 \u0199 !l \u00b0' (1;i,g @J g \u019a CB g_ \u019b jt. \u00b7u C \u0016 \u019c Y /} \u00b5 u \u00b0' a ,g n c -fl &l rm g .9-@",
    "fonts": [
      "*Arial-Bold-9625",
      "*Arial-Bold-9626",
      "*Arial-Bold-9627",
      "*Times New Roman-9598",
      "*Times New Roman-9601",
      "*Times New Roman-Italic-9606",
      "*Times New Roman-Italic-9611",
      "*Times New Roman-Italic-9612"
    ],
    "sizes": [
      6.0,
      6.5,
      9.0,
      10.0,
      13.5,
      17.0
    ]
  },
  {
    "page_number": 22,
    "bbox": [
      469.87,
      134.03,
      510.74,
      162.95
    ],
    "text": "4r@(O 0. tigi",
    "fonts": [
      "*Courier New-9632",
      "*Times New Roman-9598"
    ],
    "sizes": [
      6.0,
      16.0
    ]
  },
  {
    "page_number": 22,
    "bbox": [
      471.65,
      142.28,
      508.63,
      182.73
    ],
    "text": ". G 0 9 CD !JJ \u00ae O> 0, \u00ae \u00ae",
    "fonts": [
      "*Arial-Bold-9625",
      "*Arial-Bold-9626",
      "*Courier New-9631"
    ],
    "sizes": [
      6.5,
      8.0,
      9.0
    ]
  },
  {
    "page_number": 22,
    "bbox": [
      384.78,
      183.53,
      508.62,
      382.56
    ],
    "text": "Cl-0 {b G\\ G\\ 4 C@C\u00ae Cl \u019d[CQt\u019e 9.CS\u019f \u00ae oo u.g_@ (lb .11\\0it-!> Dl ,.,. _C> .r.r G ,[ @ g @J C\\ \"' Glrt...,,,90. \u00b7 \u00ae g \u01a0 c, \"\"' g $.) /- !':!. 8,8.r. g=CJ G\\ a ,... \u01a1c, u g9 \"\" g G\\ \u01a2g\u01a3.-_go\u01a4.r.r Cl6 N'gG ,....6 Wuc, u..\u01a5 G\\ g\u01a6 fil\u00b7coi.fi _R-@Cl|}ic,g O gCS G\\ 9 \u2022\u202299s0go.G\\6g 0oc9 ,l'l 9,-r\u00b7 \u2022 u.= (1;i cg @) G\\ g c,i \u001b,:!? > g G <O a g GGG\\Glr0-9.0g -c, rcGCJ\"> ~@)c,GI ctl\u01a7@) . G\\ N 9. NCl!b G16 \"'Cg Gc:1 <\u00bbwu...r.3\u00b7 G . GO \u00ae ..r, ,.... @1J ,g Gl Cl u ;::,, \u01a8- GD 0-. ci coG\\ gi&o \u0003&@\u0004 g \u01a99:J 9 @l g @1J _!:j. G \u00a31_ .r.\u00b7",
    "fonts": [
      "*Arial-Bold-9625",
      "*Arial-Bold-9626",
      "*Arial-Bold-9627",
      "*Arial-Bold-9630",
      "*Arial-Italic-9628",
      "*Arial-Italic-9629",
      "*Times New Roman-9598",
      "*Times New Roman-9605",
      "*Times New Roman-9607",
      "*Times New Roman-9608",
      "*Times New Roman-9609",
      "*Times New Roman-9610",
      "*Times New Roman-Italic-9606"
    ],
    "sizes": [
      4.0,
      5.0,
      6.0,
      6.000072002410889,
      6.5,
      6.500078201293945,
      8.0,
      9.0,
      9.000107765197754,
      12.5,
      14.0,
      16.0
    ]
  },
  {
    "page_number": 22,
    "bbox": [
      532.69,
      135.99,
      541.72,
      149.34
    ],
    "text": "N N",
    "fonts": [
      "*Verdana-Bold-9634"
    ],
    "sizes": [
      6.0
    ]
  },
  {
    "page_number": 22,
    "bbox": [
      533.19,
      155.92,
      541.3,
      177.52
    ],
    "text": "N 0 0 N",
    "fonts": [
      "*Times New Roman-Bold-9604"
    ],
    "sizes": [
      5.5
    ]
  },
  {
    "page_number": 22,
    "bbox": [
      520.73,
      179.43,
      557.59,
      280.77
    ],
    "text": ".Q g '& 9 - 0 \u000f\u0010 ,\u0002 9 .... -Gl",
    "fonts": [
      "*Tahoma-Bold-9635",
      "*Times New Roman-9595",
      "*Times New Roman-9598",
      "*Times New Roman-9599",
      "*Times New Roman-9600",
      "*Times New Roman-9601",
      "*Times New Roman-9602",
      "*Times New Roman-Bold-9603"
    ],
    "sizes": [
      4.0,
      6.0,
      7.0,
      9.0,
      11.0,
      14.5,
      17.0,
      70.0
    ]
  },
  {
    "page_number": 22,
    "bbox": [
      521.29,
      267.5,
      539.44,
      279.55
    ],
    "text": "0 9",
    "fonts": [
      "*Tahoma-Bold-9635"
    ],
    "sizes": [
      8.99991226196289
    ]
  },
  {
    "page_number": 22,
    "bbox": [
      520.91,
      268.79,
      541.73,
      295.11
    ],
    "text": "9 -e 9 G",
    "fonts": [
      "*Tahoma-Bold-9635",
      "*Times New Roman-Bold-9597"
    ],
    "sizes": [
      8.999927520751953,
      9.0,
      17.0
    ]
  },
  {
    "page_number": 22,
    "bbox": [
      530.57,
      287.35,
      546.16,
      359.5
    ],
    "text": "9 9 I Cl> @I \u0011",
    "fonts": [
      "*Arial-Bold-9625",
      "*Tahoma-Bold-9635",
      "*Times New Roman-9595",
      "*Times New Roman-9596"
    ],
    "sizes": [
      6.5,
      9.0,
      11.0,
      27.0
    ]
  },
  {
    "page_number": 23,
    "bbox": [
      43.72,
      87.35,
      130.5,
      148.04
    ],
    "text": "o can\u0151 g c, Ci'3CICLU\"'6 u Gl u_s>,.J a\u0152aa\u0010cr, a SJ ......O\u0153ci<fj9Cgi QC 9'9C9J",
    "fonts": [
      "*Arial-6549",
      "*Arial-6550",
      "*Times New Roman-6537"
    ],
    "sizes": [
      5.500001430511475,
      8.499956130981445,
      8.500001907348633,
      8.50009822845459,
      15.00017261505127
    ]
  },
  {
    "page_number": 23,
    "bbox": [
      45.68,
      132.86,
      129.82,
      152.96
    ],
    "text": "g@!)!;l !:l_@ c,CD",
    "fonts": [
      "*Arial-6549",
      "*Arial-6550"
    ],
    "sizes": [
      5.500065326690674,
      8.500101089477539
    ]
  },
  {
    "page_number": 23,
    "bbox": [
      44.16,
      138.01,
      132.2,
      189.71
    ],
    "text": "Q.\u00b0' g GlGl 4al9u@9.0-G..r.a,GlCS C9 g ,-,Cc,c, gC\u0154!lo.o.@)",
    "fonts": [
      "*Arial-6549",
      "*Arial-6550",
      "*Times New Roman-Italic-6539"
    ],
    "sizes": [
      5.5000481605529785,
      5.500120639801025,
      8.500075340270996,
      8.50009822845459,
      8.50010871887207,
      8.500186920166016,
      13.000149726867676
    ]
  },
  {
    "page_number": 23,
    "bbox": [
      60.58,
      173.33,
      131.49,
      197.19
    ],
    "text": "Cll\"\"O .o .oc",
    "fonts": [
      "*Arial-6549",
      "*Arial-6550"
    ],
    "sizes": [
      5.50012731552124,
      8.500197410583496
    ]
  },
  {
    "page_number": 23,
    "bbox": [
      45.29,
      181.22,
      132.22,
      232.22
    ],
    "text": "O@QJ .t11 gge> 8:lg Gl \u0155,S>--,S>--1:l g .ro 6 g c Q. u..Q.o._ gO c9 Cl Gl g_,.,., \u00b0' @!)",
    "fonts": [
      "*Arial-6549",
      "*Arial-6550"
    ],
    "sizes": [
      5.500001430511475,
      5.500063419342041,
      5.500171661376953,
      8.499916076660156,
      8.500001907348633,
      8.500005722045898,
      8.50009822845459,
      8.500265121459961
    ]
  },
  {
    "page_number": 23,
    "bbox": [
      43.53,
      216.97,
      131.34,
      286.57
    ],
    "text": "\u0156 \u00ae..r. w c9 mGl\u0157 8:J(j) N (j) v 4 @)\"' (j) cJ0 -\"O 8 c w \"' Gl @.r; N .t\"OW cG)C)U<!9g g g O Gl O \u2022\u0158 \u0159 g (j) (D,... Gl uu.90CI@@",
    "fonts": [
      "*Arial-6549",
      "*Arial-6550",
      "*Times New Roman-6527",
      "*Times New Roman-6531",
      "*Times New Roman-6548",
      "*Times New Roman-Italic-6539",
      "*Times New Roman-Italic-6547"
    ],
    "sizes": [
      5.500000476837158,
      8.500000953674316,
      8.500001907348633,
      8.500049591064453,
      8.50009822845459,
      8.500099182128906,
      9.000104904174805,
      12.00000286102295,
      12.000140190124512,
      13.00000286102295,
      13.500003814697266
    ]
  },
  {
    "page_number": 23,
    "bbox": [
      262.79,
      93.46,
      275.09,
      118.83
    ],
    "text": "....... -0.....",
    "fonts": [
      "*Arial-6549",
      "*Times New Roman-6532"
    ],
    "sizes": [
      8.000001907348633,
      8.500001907348633
    ]
  },
  {
    "page_number": 23,
    "bbox": [
      142.38,
      122.09,
      276.95,
      190.62
    ],
    "text": "Gl Gl@)OJ\u015al]) itr', \u015b(j) Cc9 \u00aec (!)GiCl\u015cQ t\"' Gl Q c, c, a &crf ft/ u.w c,t\u0002 llcWf g \u0007\b fCD[ gjO C o._ \u015du.CCIOJ CGc&[a(9[gia c",
    "fonts": [
      "*Arial-6549",
      "*Arial-6550",
      "*Arial-Bold-6554",
      "*Arial-Bold-6555",
      "*Times New Roman-6531",
      "*Times New Roman-6537",
      "*Times New Roman-6538",
      "*Times New Roman-6541",
      "*Times New Roman-6546"
    ],
    "sizes": [
      5.499983310699463,
      8.499895095825195,
      8.499974250793457,
      8.500001907348633,
      8.50021743774414,
      10.000255584716797,
      10.50000286102295,
      13.000333786010742,
      15.000384330749512,
      16.000003814697266,
      20.000003814697266,
      26.0000057220459
    ]
  },
  {
    "page_number": 23,
    "bbox": [
      143.32,
      172.05,
      273.09,
      195.06
    ],
    "text": ",El Cl g4 l'hCDg(t)",
    "fonts": [
      "*Arial-6549"
    ],
    "sizes": [
      8.50006103515625,
      8.500115394592285
    ]
  },
  {
    "page_number": 23,
    "bbox": [
      145.17,
      178.15,
      274.77,
      209.49
    ],
    "text": "C\"'-cl,l =Ul@ \u015e CJOQ Gl ,9rc>CDau g",
    "fonts": [
      "*Arial-6549",
      "*Arial-6550"
    ],
    "sizes": [
      5.500011444091797,
      8.500017166137695,
      8.50009822845459,
      8.500237464904785
    ]
  },
  {
    "page_number": 23,
    "bbox": [
      154.47,
      191.97,
      276.93,
      221.05
    ],
    "text": "Gl Gl .o \u00b0'w Gl OJ _s>,. a[o-a c, \u0011a_cr, ai\u0004",
    "fonts": [
      "*Arial-6549",
      "*Arial-6550",
      "*Times New Roman-6532",
      "*Times New Roman-6537",
      "*Times New Roman-6538",
      "*Times New Roman-Italic-6545"
    ],
    "sizes": [
      5.499963760375977,
      8.000001907348633,
      8.499943733215332,
      8.500001907348633,
      10.000001907348633,
      14.499903678894043,
      15.000003814697266
    ]
  },
  {
    "page_number": 23,
    "bbox": [
      157.24,
      209.31,
      212.58,
      231.4
    ],
    "text": "c, ,S'CG",
    "fonts": [
      "*Arial-6549"
    ],
    "sizes": [
      8.50009822845459
    ]
  },
  {
    "page_number": 23,
    "bbox": [
      212.66,
      240.73,
      226.79,
      258.26
    ],
    "text": "!",
    "fonts": [
      "*Arial-6549"
    ],
    "sizes": [
      8.50009822845459
    ]
  },
  {
    "page_number": 23,
    "bbox": [
      154.34,
      208.27,
      275.56,
      287.08
    ],
    "text": "cag lli r?o._0..B@JB o._g,.:r.r,_c::i \u0002g \u00aeg -Qg \u015f ! (i) .-c (j) Gl fJ:> _s>,.-...SJa_ ci.r.sg. g.Cl)o,{!) :JfJ:)\u0160u.C)g Gl9C!3 N \u00b0' g \u00b0'CGl ;:;.,. 96 c9 B c5 ,g e. o.. \u00ae @ c9",
    "fonts": [
      "*Arial-6549",
      "*Arial-6550",
      "*Arial-6553",
      "*Times New Roman-6536",
      "*Times New Roman-6541",
      "*Times New Roman-6544"
    ],
    "sizes": [
      5.500001430511475,
      5.500063419342041,
      8.500001907348633,
      8.50009822845459,
      11.000029563903809,
      12.50000286102295,
      18.000003814697266,
      20.000003814697266
    ]
  },
  {
    "page_number": 23,
    "bbox": [
      323.73,
      94.28,
      335.74,
      119.67
    ],
    "text": "....... ;!J",
    "fonts": [
      "*Arial-6549",
      "*Times New Roman-Italic-6542"
    ],
    "sizes": [
      8.500001907348633,
      10.000001907348633
    ]
  },
  {
    "page_number": 23,
    "bbox": [
      290.05,
      122.81,
      336.87,
      146.5
    ],
    "text": "maicio.. c, @) \u00b0'",
    "fonts": [
      "*Arial-6549",
      "*Times New Roman-6536"
    ],
    "sizes": [
      8.500001907348633,
      12.50000286102295
    ]
  },
  {
    "page_number": 23,
    "bbox": [
      287.27,
      136.11,
      337.32,
      199.24
    ],
    "text": "g .(', ! O Gl 9) 6 \u0161 1 CD 6 ,S' \u0162C> \u00b0' u.Gl -:'(> ()",
    "fonts": [
      "*Arial-6549",
      "*Arial-6550",
      "*Times New Roman-6537",
      "*Times New Roman-6543"
    ],
    "sizes": [
      5.500001430511475,
      5.500063419342041,
      8.500001907348633,
      8.50009822845459,
      8.500288963317871,
      15.000510215759277,
      16.00018310546875
    ]
  },
  {
    "page_number": 23,
    "bbox": [
      299.18,
      192.35,
      337.6,
      273.91
    ],
    "text": "Q [D@) c, It) c\u00b0' \u2022 u ..r, Gl c, g_ g Ou O Gl ,SJ CG s .r, g u. 6 g\u00b7..s,a",
    "fonts": [
      "*Arial-6549",
      "*Arial-6550",
      "*Arial-6552",
      "*Times New Roman-6525",
      "*Times New Roman-6527",
      "*Times New Roman-6537",
      "*Times New Roman-6538"
    ],
    "sizes": [
      4.0000457763671875,
      5.500001430511475,
      5.500063419342041,
      8.500001907348633,
      8.50009822845459,
      10.000115394592285,
      11.50013256072998,
      12.000138282775879,
      15.000003814697266
    ]
  },
  {
    "page_number": 23,
    "bbox": [
      300.01,
      257.56,
      336.98,
      284.39
    ],
    "text": "\u00b0' 6 c, .l'O u g",
    "fonts": [
      "*Arial-6549",
      "*Times New Roman-6537"
    ],
    "sizes": [
      8.500001907348633,
      8.50009822845459,
      15.00017261505127
    ]
  },
  {
    "page_number": 23,
    "bbox": [
      383.5,
      93.54,
      396.09,
      120.73
    ],
    "text": "....... -0 u",
    "fonts": [
      "*Arial-6549"
    ],
    "sizes": [
      8.500001907348633
    ]
  },
  {
    "page_number": 23,
    "bbox": [
      345.12,
      122.63,
      399.47,
      194.73
    ],
    "text": "@J9CDQ: u @) Gl ex u a Q. 6 ciEIJ6 Olf9.9. u C \u0163 Ol(na, c co Gl",
    "fonts": [
      "*Arial-6549",
      "*Arial-6550",
      "*Times New Roman-6526",
      "*Times New Roman-6530",
      "*Times New Roman-6536",
      "*Times New Roman-6538"
    ],
    "sizes": [
      5.500063419342041,
      6.0000691413879395,
      8.500001907348633,
      8.50009822845459,
      10.000115394592285,
      12.500144004821777,
      18.500213623046875
    ]
  },
  {
    "page_number": 23,
    "bbox": [
      347.39,
      193.92,
      397.69,
      284.36
    ],
    "text": "\u0164[;) \u0165@) m CG @J.ro c, i ,S' IT> (i'3 Cl O C\"' D 6 g \u0166 6 @ 8 g u CD \u00ae\u0167! fl O 9J",
    "fonts": [
      "*Arial-6549",
      "*Times New Roman-6535",
      "*Times New Roman-6537",
      "*Times New Roman-6541",
      "*Times New Roman-Italic-6539"
    ],
    "sizes": [
      8.500001907348633,
      8.50009822845459,
      13.000149726867676,
      14.000161170959473,
      15.000003814697266,
      20.000003814697266
    ]
  },
  {
    "page_number": 23,
    "bbox": [
      480.66,
      96.65,
      492.3,
      120.11
    ],
    "text": "....... -0",
    "fonts": [
      "*Arial-6549"
    ],
    "sizes": [
      8.500001907348633
    ]
  },
  {
    "page_number": 23,
    "bbox": [
      405.61,
      121.0,
      495.26,
      200.31
    ],
    "text": "-OO OJ CJGl lT'>Q:a CJCI', ci g ci C 8 C u D \u00b0' 6\"' g \u0168 9. u B o._ g o._Gl .r, \u0169c, ,.s>-9Bci t;J 6 ;fJ \u016a a, u. @)\u016b u 9. .r. 9i a> Cg[/JmS>\u016c",
    "fonts": [
      "*Arial-6549",
      "*Arial-6550",
      "*Times New Roman-6525",
      "*Times New Roman-6527",
      "*Times New Roman-6528"
    ],
    "sizes": [
      4.000094413757324,
      5.500001430511475,
      8.499945640563965,
      8.500001907348633,
      8.50009822845459,
      8.500174522399902,
      8.500201225280762,
      12.00000286102295,
      23.0000057220459
    ]
  },
  {
    "page_number": 23,
    "bbox": [
      408.48,
      185.44,
      492.5,
      256.32
    ],
    "text": "Gl @) 9J c, Cl \u000ei\u000fo&.roai a u 9J 8 u. g ...::r Gl CD @ YJ -Ill a CD g u m\u0004 e.,&cr,<g)eaC>@oe5 0 u0l",
    "fonts": [
      "*Arial-6549",
      "*Arial-6550",
      "*Arial-6551",
      "*Times New Roman-6535",
      "*Times New Roman-6536",
      "*Times New Roman-6537",
      "*Times New Roman-6540",
      "*Times New Roman-Italic-6539"
    ],
    "sizes": [
      5.500063419342041,
      7.999958515167236,
      8.499903678894043,
      8.499956130981445,
      8.499960899353027,
      8.500001907348633,
      8.50009822845459,
      9.000001907348633,
      12.499935150146484,
      13.000042915344238,
      14.00000286102295,
      14.000046730041504,
      14.999930381774902,
      15.000003814697266,
      15.00017261505127
    ]
  },
  {
    "page_number": 23,
    "bbox": [
      411.07,
      238.71,
      494.08,
      283.78
    ],
    "text": "@)\u016d \"'c, g_ c c, \u00ae \u016e!l!!h gGl (j)fl@GJ(n 8. CJ c, CJ er, IT>",
    "fonts": [
      "*Arial-6549",
      "*Arial-6550",
      "*Times New Roman-6535",
      "*Times New Roman-6536",
      "*Times New Roman-6537",
      "*Times New Roman-6538"
    ],
    "sizes": [
      5.500001430511475,
      8.500001907348633,
      10.000001907348633,
      12.50000286102295,
      14.00000286102295,
      15.000003814697266
    ]
  },
  {
    "page_number": 23,
    "bbox": [
      504.35,
      116.55,
      516.01,
      138.81
    ],
    "text": "0. Gl",
    "fonts": [
      "*Arial-6549"
    ],
    "sizes": [
      8.500001907348633
    ]
  },
  {
    "page_number": 23,
    "bbox": [
      504.34,
      128.73,
      517.41,
      166.6
    ],
    "text": "El. cc, c,.r,",
    "fonts": [
      "*Arial-6549"
    ],
    "sizes": [
      8.500001907348633
    ]
  },
  {
    "page_number": 23,
    "bbox": [
      504.05,
      161.07,
      518.35,
      231.42
    ],
    "text": "C: -0Gl Q \u0004-g c u",
    "fonts": [
      "*Arial-6549",
      "*Times New Roman-6527",
      "*Times New Roman-6528"
    ],
    "sizes": [
      8.500001907348633,
      12.00000286102295,
      23.0000057220459
    ]
  },
  {
    "page_number": 23,
    "bbox": [
      506.88,
      225.3,
      519.11,
      259.49
    ],
    "text": "Cl OJ a",
    "fonts": [
      "*Arial-6549",
      "*Times New Roman-6526"
    ],
    "sizes": [
      8.500001907348633,
      18.500003814697266
    ]
  },
  {
    "page_number": 23,
    "bbox": [
      530.11,
      57.39,
      554.55,
      143.61
    ],
    "text": "N 0 0 N \u0007 g -a 9 00 O qi",
    "fonts": [
      "*Courier New-6556",
      "*Microsoft Sans Serif-Bold-6557",
      "*Tahoma-Bold-6558",
      "*Times New Roman-6528",
      "*Times New Roman-6532",
      "*Times New Roman-Bold-6534",
      "*Times New Roman-Italic-6533"
    ],
    "sizes": [
      4.000000953674316,
      5.500001430511475,
      8.000001907348633,
      9.000001907348633,
      11.00000286102295,
      23.0000057220459
    ]
  },
  {
    "page_number": 23,
    "bbox": [
      529.83,
      139.38,
      551.3,
      175.13
    ],
    "text": "\u016f 9. cJ O 9 '\"' -G",
    "fonts": [
      "*Arial-6549",
      "*Times New Roman-6531"
    ],
    "sizes": [
      8.500001907348633,
      13.00000286102295
    ]
  },
  {
    "page_number": 23,
    "bbox": [
      530.83,
      170.11,
      551.55,
      198.22
    ],
    "text": "0 9 94 g &",
    "fonts": [
      "*Microsoft Sans Serif-Bold-6557"
    ],
    "sizes": [
      9.000001907348633
    ]
  },
  {
    "page_number": 23,
    "bbox": [
      540.27,
      190.18,
      551.74,
      236.42
    ],
    "text": "9 9 0. 9. .,.,",
    "fonts": [
      "*Arial-6549",
      "*Times New Roman-6531"
    ],
    "sizes": [
      8.500001907348633,
      13.00000286102295
    ]
  },
  {
    "page_number": 23,
    "bbox": [
      541.84,
      232.65,
      555.82,
      268.35
    ],
    "text": "Ci) I",
    "fonts": [
      "*Times New Roman-6529",
      "*Times New Roman-6530"
    ],
    "sizes": [
      6.000001430511475,
      26.50000762939453
    ]
  },
  {
    "page_number": 23,
    "bbox": [
      542.04,
      261.28,
      551.96,
      280.56
    ],
    "text": "N \\.,J",
    "fonts": [
      "*Arial-6549",
      "*Times New Roman-6525"
    ],
    "sizes": [
      4.000000953674316,
      8.500001907348633
    ]
  }
]